setup.py
distributions/Binomialdistribution.py
distributions/Gaussiandistribution.py
distributions/Generaldistribution.py
distributions/__init__.py
weiheng_distributions.egg-info/PKG-INFO
weiheng_distributions.egg-info/SOURCES.txt
weiheng_distributions.egg-info/dependency_links.txt
weiheng_distributions.egg-info/not-zip-safe
weiheng_distributions.egg-info/top_level.txt